mcp_server_dbase/__init__.py
mcp_server_dbase/server.py
mcp_server_dbase-0.6.2.dist-info/METADATA
mcp_server_dbase-0.6.2.dist-info/WHEEL
mcp_server_dbase-0.6.2.dist-info/entry_points.txt
mcp_server_dbase-0.6.2.dist-info/RECORD
