Metadata-Version: 2.3
Name: mcp-server-dbase
Version: 0.6.2
Summary: A simple dbase MCP server
Requires-Python: >=3.10
Requires-Dist: mcp>=1.0.0
